{"nodes": [{"id": "users_juandiego_projects_mentex_app_screens_profile_jsx", "label": "profile.jsx", "file_type": "code", "source_file": "/Users/juandiego/Projects/Mentex app/screens/profile.jsx", "source_location": "L1"}, {"id": "screens_profile_getsocialbrand", "label": "_getSocialBrand()", "file_type": "code", "source_file": "/Users/juandiego/Projects/Mentex app/screens/profile.jsx", "source_location": "L22"}, {"id": "screens_profile_opensocialurl", "label": "_openSocialUrl()", "file_type": "code", "source_file": "/Users/juandiego/Projects/Mentex app/screens/profile.jsx", "source_location": "L52"}, {"id": "screens_profile_buildachievements", "label": "_buildAchievements()", "file_type": "code", "source_file": "/Users/juandiego/Projects/Mentex app/screens/profile.jsx", "source_location": "L130"}, {"id": "screens_profile_buildachievementsforuser", "label": "_buildAchievementsForUser()", "file_type": "code", "source_file": "/Users/juandiego/Projects/Mentex app/screens/profile.jsx", "source_location": "L142"}, {"id": "screens_profile_useprofile", "label": "useProfile()", "file_type": "code", "source_file": "/Users/juandiego/Projects/Mentex app/screens/profile.jsx", "source_location": "L226"}, {"id": "screens_profile_editprofilesheet", "label": "EditProfileSheet()", "file_type": "code", "source_file": "/Users/juandiego/Projects/Mentex app/screens/profile.jsx", "source_location": "L237"}, {"id": "screens_profile_achievementbadge", "label": "AchievementBadge()", "file_type": "code", "source_file": "/Users/juandiego/Projects/Mentex app/screens/profile.jsx", "source_location": "L550"}, {"id": "screens_profile_achievementcard", "label": "AchievementCard()", "file_type": "code", "source_file": "/Users/juandiego/Projects/Mentex app/screens/profile.jsx", "source_location": "L588"}, {"id": "screens_profile_achievementbadgev2", "label": "AchievementBadgeV2()", "file_type": "code", "source_file": "/Users/juandiego/Projects/Mentex app/screens/profile.jsx", "source_location": "L657"}, {"id": "screens_profile_achievementcardgrid", "label": "AchievementCardGrid()", "file_type": "code", "source_file": "/Users/juandiego/Projects/Mentex app/screens/profile.jsx", "source_location": "L680"}, {"id": "screens_profile_profilereviewcard", "label": "ProfileReviewCard()", "file_type": "code", "source_file": "/Users/juandiego/Projects/Mentex app/screens/profile.jsx", "source_location": "L786"}, {"id": "screens_profile_useuserreviews", "label": "useUserReviews()", "file_type": "code", "source_file": "/Users/juandiego/Projects/Mentex app/screens/profile.jsx", "source_location": "L1031"}, {"id": "screens_profile_statsdonut", "label": "StatsDonut()", "file_type": "code", "source_file": "/Users/juandiego/Projects/Mentex app/screens/profile.jsx", "source_location": "L1043"}, {"id": "screens_profile_buildareapaths", "label": "_buildAreaPaths()", "file_type": "code", "source_file": "/Users/juandiego/Projects/Mentex app/screens/profile.jsx", "source_location": "L1095"}, {"id": "screens_profile_derivestatsfor", "label": "_deriveStatsFor()", "file_type": "code", "source_file": "/Users/juandiego/Projects/Mentex app/screens/profile.jsx", "source_location": "L1131"}, {"id": "screens_profile_profilestatstab", "label": "ProfileStatsTab()", "file_type": "code", "source_file": "/Users/juandiego/Projects/Mentex app/screens/profile.jsx", "source_location": "L1279"}, {"id": "screens_profile_heronextachievement", "label": "HeroNextAchievement()", "file_type": "code", "source_file": "/Users/juandiego/Projects/Mentex app/screens/profile.jsx", "source_location": "L2210"}, {"id": "screens_profile_swipeableherocarousel", "label": "SwipeableHeroCarousel()", "file_type": "code", "source_file": "/Users/juandiego/Projects/Mentex app/screens/profile.jsx", "source_location": "L2302"}, {"id": "screens_profile_awardstab", "label": "AwardsTab()", "file_type": "code", "source_file": "/Users/juandiego/Projects/Mentex app/screens/profile.jsx", "source_location": "L2388"}, {"id": "screens_profile_profilescreen", "label": "ProfileScreen()", "file_type": "code", "source_file": "/Users/juandiego/Projects/Mentex app/screens/profile.jsx", "source_location": "L2464"}], "edges": [{"source": "users_juandiego_projects_mentex_app_screens_profile_jsx", "target": "screens_profile_getsocialbrand", "relation": "contains", "confidence": "EXTRACTED", "source_file": "/Users/juandiego/Projects/Mentex app/screens/profile.jsx", "source_location": "L22", "weight": 1.0}, {"source": "users_juandiego_projects_mentex_app_screens_profile_jsx", "target": "screens_profile_opensocialurl", "relation": "contains", "confidence": "EXTRACTED", "source_file": "/Users/juandiego/Projects/Mentex app/screens/profile.jsx", "source_location": "L52", "weight": 1.0}, {"source": "users_juandiego_projects_mentex_app_screens_profile_jsx", "target": "screens_profile_buildachievements", "relation": "contains", "confidence": "EXTRACTED", "source_file": "/Users/juandiego/Projects/Mentex app/screens/profile.jsx", "source_location": "L130", "weight": 1.0}, {"source": "users_juandiego_projects_mentex_app_screens_profile_jsx", "target": "screens_profile_buildachievementsforuser", "relation": "contains", "confidence": "EXTRACTED", "source_file": "/Users/juandiego/Projects/Mentex app/screens/profile.jsx", "source_location": "L142", "weight": 1.0}, {"source": "users_juandiego_projects_mentex_app_screens_profile_jsx", "target": "screens_profile_useprofile", "relation": "contains", "confidence": "EXTRACTED", "source_file": "/Users/juandiego/Projects/Mentex app/screens/profile.jsx", "source_location": "L226", "weight": 1.0}, {"source": "users_juandiego_projects_mentex_app_screens_profile_jsx", "target": "screens_profile_editprofilesheet", "relation": "contains", "confidence": "EXTRACTED", "source_file": "/Users/juandiego/Projects/Mentex app/screens/profile.jsx", "source_location": "L237", "weight": 1.0}, {"source": "users_juandiego_projects_mentex_app_screens_profile_jsx", "target": "screens_profile_achievementbadge", "relation": "contains", "confidence": "EXTRACTED", "source_file": "/Users/juandiego/Projects/Mentex app/screens/profile.jsx", "source_location": "L550", "weight": 1.0}, {"source": "users_juandiego_projects_mentex_app_screens_profile_jsx", "target": "screens_profile_achievementcard", "relation": "contains", "confidence": "EXTRACTED", "source_file": "/Users/juandiego/Projects/Mentex app/screens/profile.jsx", "source_location": "L588", "weight": 1.0}, {"source": "users_juandiego_projects_mentex_app_screens_profile_jsx", "target": "screens_profile_achievementbadgev2", "relation": "contains", "confidence": "EXTRACTED", "source_file": "/Users/juandiego/Projects/Mentex app/screens/profile.jsx", "source_location": "L657", "weight": 1.0}, {"source": "users_juandiego_projects_mentex_app_screens_profile_jsx", "target": "screens_profile_achievementcardgrid", "relation": "contains", "confidence": "EXTRACTED", "source_file": "/Users/juandiego/Projects/Mentex app/screens/profile.jsx", "source_location": "L680", "weight": 1.0}, {"source": "users_juandiego_projects_mentex_app_screens_profile_jsx", "target": "screens_profile_profilereviewcard", "relation": "contains", "confidence": "EXTRACTED", "source_file": "/Users/juandiego/Projects/Mentex app/screens/profile.jsx", "source_location": "L786", "weight": 1.0}, {"source": "users_juandiego_projects_mentex_app_screens_profile_jsx", "target": "screens_profile_useuserreviews", "relation": "contains", "confidence": "EXTRACTED", "source_file": "/Users/juandiego/Projects/Mentex app/screens/profile.jsx", "source_location": "L1031", "weight": 1.0}, {"source": "users_juandiego_projects_mentex_app_screens_profile_jsx", "target": "screens_profile_statsdonut", "relation": "contains", "confidence": "EXTRACTED", "source_file": "/Users/juandiego/Projects/Mentex app/screens/profile.jsx", "source_location": "L1043", "weight": 1.0}, {"source": "users_juandiego_projects_mentex_app_screens_profile_jsx", "target": "screens_profile_buildareapaths", "relation": "contains", "confidence": "EXTRACTED", "source_file": "/Users/juandiego/Projects/Mentex app/screens/profile.jsx", "source_location": "L1095", "weight": 1.0}, {"source": "users_juandiego_projects_mentex_app_screens_profile_jsx", "target": "screens_profile_derivestatsfor", "relation": "contains", "confidence": "EXTRACTED", "source_file": "/Users/juandiego/Projects/Mentex app/screens/profile.jsx", "source_location": "L1131", "weight": 1.0}, {"source": "users_juandiego_projects_mentex_app_screens_profile_jsx", "target": "screens_profile_profilestatstab", "relation": "contains", "confidence": "EXTRACTED", "source_file": "/Users/juandiego/Projects/Mentex app/screens/profile.jsx", "source_location": "L1279", "weight": 1.0}, {"source": "users_juandiego_projects_mentex_app_screens_profile_jsx", "target": "screens_profile_heronextachievement", "relation": "contains", "confidence": "EXTRACTED", "source_file": "/Users/juandiego/Projects/Mentex app/screens/profile.jsx", "source_location": "L2210", "weight": 1.0}, {"source": "users_juandiego_projects_mentex_app_screens_profile_jsx", "target": "screens_profile_swipeableherocarousel", "relation": "contains", "confidence": "EXTRACTED", "source_file": "/Users/juandiego/Projects/Mentex app/screens/profile.jsx", "source_location": "L2302", "weight": 1.0}, {"source": "users_juandiego_projects_mentex_app_screens_profile_jsx", "target": "screens_profile_awardstab", "relation": "contains", "confidence": "EXTRACTED", "source_file": "/Users/juandiego/Projects/Mentex app/screens/profile.jsx", "source_location": "L2388", "weight": 1.0}, {"source": "users_juandiego_projects_mentex_app_screens_profile_jsx", "target": "screens_profile_profilescreen", "relation": "contains", "confidence": "EXTRACTED", "source_file": "/Users/juandiego/Projects/Mentex app/screens/profile.jsx", "source_location": "L2464", "weight": 1.0}, {"source": "screens_profile_buildachievementsforuser", "target": "screens_profile_buildachievements", "relation": "calls", "confidence": "EXTRACTED", "source_file": "/Users/juandiego/Projects/Mentex app/screens/profile.jsx", "source_location": "L143", "weight": 1.0}, {"source": "screens_profile_profilestatstab", "target": "screens_profile_useprofile", "relation": "calls", "confidence": "EXTRACTED", "source_file": "/Users/juandiego/Projects/Mentex app/screens/profile.jsx", "source_location": "L1280", "weight": 1.0}, {"source": "screens_profile_profilestatstab", "target": "screens_profile_buildareapaths", "relation": "calls", "confidence": "EXTRACTED", "source_file": "/Users/juandiego/Projects/Mentex app/screens/profile.jsx", "source_location": "L1364", "weight": 1.0}, {"source": "screens_profile_profilescreen", "target": "screens_profile_useprofile", "relation": "calls", "confidence": "EXTRACTED", "source_file": "/Users/juandiego/Projects/Mentex app/screens/profile.jsx", "source_location": "L2465", "weight": 1.0}, {"source": "screens_profile_profilescreen", "target": "screens_profile_useuserreviews", "relation": "calls", "confidence": "EXTRACTED", "source_file": "/Users/juandiego/Projects/Mentex app/screens/profile.jsx", "source_location": "L2472", "weight": 1.0}], "raw_calls": [{"caller_nid": "screens_profile_opensocialurl", "callee": "trim", "source_file": "/Users/juandiego/Projects/Mentex app/screens/profile.jsx", "source_location": "L53"}, {"caller_nid": "screens_profile_opensocialurl", "callee": "replace", "source_file": "/Users/juandiego/Projects/Mentex app/screens/profile.jsx", "source_location": "L53"}, {"caller_nid": "screens_profile_opensocialurl", "callee": "String", "source_file": "/Users/juandiego/Projects/Mentex app/screens/profile.jsx", "source_location": "L53"}, {"caller_nid": "screens_profile_opensocialurl", "callee": "replace", "source_file": "/Users/juandiego/Projects/Mentex app/screens/profile.jsx", "source_location": "L60"}, {"caller_nid": "screens_profile_opensocialurl", "callee": "encodeURIComponent", "source_file": "/Users/juandiego/Projects/Mentex app/screens/profile.jsx", "source_location": "L61"}, {"caller_nid": "screens_profile_buildachievements", "callee": "map", "source_file": "/Users/juandiego/Projects/Mentex app/screens/profile.jsx", "source_location": "L131"}, {"caller_nid": "screens_profile_buildachievementsforuser", "callee": "charCodeAt", "source_file": "/Users/juandiego/Projects/Mentex app/screens/profile.jsx", "source_location": "L144"}, {"caller_nid": "screens_profile_buildachievementsforuser", "callee": "max", "source_file": "/Users/juandiego/Projects/Mentex app/screens/profile.jsx", "source_location": "L145"}, {"caller_nid": "screens_profile_buildachievementsforuser", "callee": "max", "source_file": "/Users/juandiego/Projects/Mentex app/screens/profile.jsx", "source_location": "L150"}, {"caller_nid": "screens_profile_buildachievementsforuser", "callee": "max", "source_file": "/Users/juandiego/Projects/Mentex app/screens/profile.jsx", "source_location": "L151"}, {"caller_nid": "screens_profile_buildachievementsforuser", "callee": "min", "source_file": "/Users/juandiego/Projects/Mentex app/screens/profile.jsx", "source_location": "L151"}, {"caller_nid": "screens_profile_buildachievementsforuser", "callee": "max", "source_file": "/Users/juandiego/Projects/Mentex app/screens/profile.jsx", "source_location": "L153"}, {"caller_nid": "screens_profile_buildachievementsforuser", "callee": "round", "source_file": "/Users/juandiego/Projects/Mentex app/screens/profile.jsx", "source_location": "L153"}, {"caller_nid": "screens_profile_buildachievementsforuser", "callee": "max", "source_file": "/Users/juandiego/Projects/Mentex app/screens/profile.jsx", "source_location": "L154"}, {"caller_nid": "screens_profile_buildachievementsforuser", "callee": "round", "source_file": "/Users/juandiego/Projects/Mentex app/screens/profile.jsx", "source_location": "L154"}, {"caller_nid": "screens_profile_buildachievementsforuser", "callee": "max", "source_file": "/Users/juandiego/Projects/Mentex app/screens/profile.jsx", "source_location": "L156"}, {"caller_nid": "screens_profile_buildachievementsforuser", "callee": "round", "source_file": "/Users/juandiego/Projects/Mentex app/screens/profile.jsx", "source_location": "L156"}, {"caller_nid": "screens_profile_buildachievementsforuser", "callee": "max", "source_file": "/Users/juandiego/Projects/Mentex app/screens/profile.jsx", "source_location": "L157"}, {"caller_nid": "screens_profile_buildachievementsforuser", "callee": "round", "source_file": "/Users/juandiego/Projects/Mentex app/screens/profile.jsx", "source_location": "L157"}, {"caller_nid": "screens_profile_buildachievementsforuser", "callee": "map", "source_file": "/Users/juandiego/Projects/Mentex app/screens/profile.jsx", "source_location": "L160"}, {"caller_nid": "screens_profile_useprofile", "callee": "useReducer", "source_file": "/Users/juandiego/Projects/Mentex app/screens/profile.jsx", "source_location": "L227"}, {"caller_nid": "screens_profile_useprofile", "callee": "useEffect", "source_file": "/Users/juandiego/Projects/Mentex app/screens/profile.jsx", "source_location": "L228"}, {"caller_nid": "screens_profile_useprofile", "callee": "get", "source_file": "/Users/juandiego/Projects/Mentex app/screens/profile.jsx", "source_location": "L233"}, {"caller_nid": "screens_profile_editprofilesheet", "callee": "useState", "source_file": "/Users/juandiego/Projects/Mentex app/screens/profile.jsx", "source_location": "L238"}, {"caller_nid": "screens_profile_editprofilesheet", "callee": "useState", "source_file": "/Users/juandiego/Projects/Mentex app/screens/profile.jsx", "source_location": "L239"}, {"caller_nid": "screens_profile_editprofilesheet", "callee": "useState", "source_file": "/Users/juandiego/Projects/Mentex app/screens/profile.jsx", "source_location": "L240"}, {"caller_nid": "screens_profile_editprofilesheet", "callee": "useState", "source_file": "/Users/juandiego/Projects/Mentex app/screens/profile.jsx", "source_location": "L241"}, {"caller_nid": "screens_profile_editprofilesheet", "callee": "useState", "source_file": "/Users/juandiego/Projects/Mentex app/screens/profile.jsx", "source_location": "L242"}, {"caller_nid": "screens_profile_editprofilesheet", "callee": "useState", "source_file": "/Users/juandiego/Projects/Mentex app/screens/profile.jsx", "source_location": "L243"}, {"caller_nid": "screens_profile_editprofilesheet", "callee": "useRef", "source_file": "/Users/juandiego/Projects/Mentex app/screens/profile.jsx", "source_location": "L246"}, {"caller_nid": "screens_profile_editprofilesheet", "callee": "useEffect", "source_file": "/Users/juandiego/Projects/Mentex app/screens/profile.jsx", "source_location": "L248"}, {"caller_nid": "screens_profile_editprofilesheet", "callee": "stringify", "source_file": "/Users/juandiego/Projects/Mentex app/screens/profile.jsx", "source_location": "L256"}, {"caller_nid": "screens_profile_editprofilesheet", "callee": "map", "source_file": "/Users/juandiego/Projects/Mentex app/screens/profile.jsx", "source_location": "L256"}, {"caller_nid": "screens_profile_editprofilesheet", "callee": "stringify", "source_file": "/Users/juandiego/Projects/Mentex app/screens/profile.jsx", "source_location": "L257"}, {"caller_nid": "screens_profile_editprofilesheet", "callee": "map", "source_file": "/Users/juandiego/Projects/Mentex app/screens/profile.jsx", "source_location": "L257"}, {"caller_nid": "screens_profile_editprofilesheet", "callee": "trim", "source_file": "/Users/juandiego/Projects/Mentex app/screens/profile.jsx", "source_location": "L258"}, {"caller_nid": "screens_profile_editprofilesheet", "callee": "trim", "source_file": "/Users/juandiego/Projects/Mentex app/screens/profile.jsx", "source_location": "L258"}, {"caller_nid": "screens_profile_editprofilesheet", "callee": "trim", "source_file": "/Users/juandiego/Projects/Mentex app/screens/profile.jsx", "source_location": "L259"}, {"caller_nid": "screens_profile_editprofilesheet", "callee": "trim", "source_file": "/Users/juandiego/Projects/Mentex app/screens/profile.jsx", "source_location": "L259"}, {"caller_nid": "screens_profile_editprofilesheet", "callee": "trim", "source_file": "/Users/juandiego/Projects/Mentex app/screens/profile.jsx", "source_location": "L260"}, {"caller_nid": "screens_profile_editprofilesheet", "callee": "trim", "source_file": "/Users/juandiego/Projects/Mentex app/screens/profile.jsx", "source_location": "L261"}, {"caller_nid": "screens_profile_editprofilesheet", "callee": "map", "source_file": "/Users/juandiego/Projects/Mentex app/screens/profile.jsx", "source_location": "L377"}, {"caller_nid": "screens_profile_editprofilesheet", "callee": "map", "source_file": "/Users/juandiego/Projects/Mentex app/screens/profile.jsx", "source_location": "L435"}, {"caller_nid": "screens_profile_achievementcard", "callee": "min", "source_file": "/Users/juandiego/Projects/Mentex app/screens/profile.jsx", "source_location": "L589"}, {"caller_nid": "screens_profile_achievementcard", "callee": "round", "source_file": "/Users/juandiego/Projects/Mentex app/screens/profile.jsx", "source_location": "L644"}, {"caller_nid": "screens_profile_achievementbadgev2", "callee": "round", "source_file": "/Users/juandiego/Projects/Mentex app/screens/profile.jsx", "source_location": "L668"}, {"caller_nid": "screens_profile_achievementcardgrid", "callee": "min", "source_file": "/Users/juandiego/Projects/Mentex app/screens/profile.jsx", "source_location": "L682"}, {"caller_nid": "screens_profile_profilereviewcard", "callee": "useState", "source_file": "/Users/juandiego/Projects/Mentex app/screens/profile.jsx", "source_location": "L787"}, {"caller_nid": "screens_profile_profilereviewcard", "callee": "useState", "source_file": "/Users/juandiego/Projects/Mentex app/screens/profile.jsx", "source_location": "L788"}, {"caller_nid": "screens_profile_profilereviewcard", "callee": "useCommentCount", "source_file": "/Users/juandiego/Projects/Mentex app/screens/profile.jsx", "source_location": "L791"}, {"caller_nid": "screens_profile_profilereviewcard", "callee": "formatRelative", "source_file": "/Users/juandiego/Projects/Mentex app/screens/profile.jsx", "source_location": "L865"}, {"caller_nid": "screens_profile_profilereviewcard", "callee": "map", "source_file": "/Users/juandiego/Projects/Mentex app/screens/profile.jsx", "source_location": "L870"}, {"caller_nid": "screens_profile_profilereviewcard", "callee": "from", "source_file": "/Users/juandiego/Projects/Mentex app/screens/profile.jsx", "source_location": "L870"}, {"caller_nid": "screens_profile_profilereviewcard", "callee": "map", "source_file": "/Users/juandiego/Projects/Mentex app/screens/profile.jsx", "source_location": "L982"}, {"caller_nid": "screens_profile_useuserreviews", "callee": "useReducer", "source_file": "/Users/juandiego/Projects/Mentex app/screens/profile.jsx", "source_location": "L1032"}, {"caller_nid": "screens_profile_useuserreviews", "callee": "useEffect", "source_file": "/Users/juandiego/Projects/Mentex app/screens/profile.jsx", "source_location": "L1033"}, {"caller_nid": "screens_profile_useuserreviews", "callee": "list", "source_file": "/Users/juandiego/Projects/Mentex app/screens/profile.jsx", "source_location": "L1038"}, {"caller_nid": "screens_profile_statsdonut", "callee": "reduce", "source_file": "/Users/juandiego/Projects/Mentex app/screens/profile.jsx", "source_location": "L1044"}, {"caller_nid": "screens_profile_statsdonut", "callee": "map", "source_file": "/Users/juandiego/Projects/Mentex app/screens/profile.jsx", "source_location": "L1051"}, {"caller_nid": "screens_profile_buildareapaths", "callee": "min", "source_file": "/Users/juandiego/Projects/Mentex app/screens/profile.jsx", "source_location": "L1097"}, {"caller_nid": "screens_profile_buildareapaths", "callee": "max", "source_file": "/Users/juandiego/Projects/Mentex app/screens/profile.jsx", "source_location": "L1097"}, {"caller_nid": "screens_profile_buildareapaths", "callee": "max", "source_file": "/Users/juandiego/Projects/Mentex app/screens/profile.jsx", "source_location": "L1098"}, {"caller_nid": "screens_profile_buildareapaths", "callee": "map", "source_file": "/Users/juandiego/Projects/Mentex app/screens/profile.jsx", "source_location": "L1099"}, {"caller_nid": "screens_profile_buildareapaths", "callee": "reduce", "source_file": "/Users/juandiego/Projects/Mentex app/screens/profile.jsx", "source_location": "L1105"}, {"caller_nid": "screens_profile_derivestatsfor", "callee": "from", "source_file": "/Users/juandiego/Projects/Mentex app/screens/profile.jsx", "source_location": "L1155"}, {"caller_nid": "screens_profile_derivestatsfor", "callee": "from", "source_file": "/Users/juandiego/Projects/Mentex app/screens/profile.jsx", "source_location": "L1161"}, {"caller_nid": "screens_profile_derivestatsfor", "callee": "map", "source_file": "/Users/juandiego/Projects/Mentex app/screens/profile.jsx", "source_location": "L1162"}, {"caller_nid": "screens_profile_derivestatsfor", "callee": "slice", "source_file": "/Users/juandiego/Projects/Mentex app/screens/profile.jsx", "source_location": "L1162"}, {"caller_nid": "screens_profile_derivestatsfor", "callee": "charCodeAt", "source_file": "/Users/juandiego/Projects/Mentex app/screens/profile.jsx", "source_location": "L1177"}, {"caller_nid": "screens_profile_derivestatsfor", "callee": "max", "source_file": "/Users/juandiego/Projects/Mentex app/screens/profile.jsx", "source_location": "L1178"}, {"caller_nid": "screens_profile_derivestatsfor", "callee": "max", "source_file": "/Users/juandiego/Projects/Mentex app/screens/profile.jsx", "source_location": "L1183"}, {"caller_nid": "screens_profile_derivestatsfor", "callee": "toFixed", "source_file": "/Users/juandiego/Projects/Mentex app/screens/profile.jsx", "source_location": "L1184"}, {"caller_nid": "screens_profile_derivestatsfor", "callee": "max", "source_file": "/Users/juandiego/Projects/Mentex app/screens/profile.jsx", "source_location": "L1185"}, {"caller_nid": "screens_profile_derivestatsfor", "callee": "round", "source_file": "/Users/juandiego/Projects/Mentex app/screens/profile.jsx", "source_location": "L1185"}, {"caller_nid": "screens_profile_derivestatsfor", "callee": "toFixed", "source_file": "/Users/juandiego/Projects/Mentex app/screens/profile.jsx", "source_location": "L1191"}, {"caller_nid": "screens_profile_derivestatsfor", "callee": "toFixed", "source_file": "/Users/juandiego/Projects/Mentex app/screens/profile.jsx", "source_location": "L1192"}, {"caller_nid": "screens_profile_derivestatsfor", "callee": "toFixed", "source_file": "/Users/juandiego/Projects/Mentex app/screens/profile.jsx", "source_location": "L1193"}, {"caller_nid": "screens_profile_derivestatsfor", "callee": "toFixed", "source_file": "/Users/juandiego/Projects/Mentex app/screens/profile.jsx", "source_location": "L1194"}, {"caller_nid": "screens_profile_derivestatsfor", "callee": "round", "source_file": "/Users/juandiego/Projects/Mentex app/screens/profile.jsx", "source_location": "L1199"}, {"caller_nid": "screens_profile_derivestatsfor", "callee": "round", "source_file": "/Users/juandiego/Projects/Mentex app/screens/profile.jsx", "source_location": "L1200"}, {"caller_nid": "screens_profile_derivestatsfor", "callee": "round", "source_file": "/Users/juandiego/Projects/Mentex app/screens/profile.jsx", "source_location": "L1201"}, {"caller_nid": "screens_profile_derivestatsfor", "callee": "round", "source_file": "/Users/juandiego/Projects/Mentex app/screens/profile.jsx", "source_location": "L1202"}, {"caller_nid": "screens_profile_derivestatsfor", "callee": "round", "source_file": "/Users/juandiego/Projects/Mentex app/screens/profile.jsx", "source_location": "L1203"}, {"caller_nid": "screens_profile_derivestatsfor", "callee": "from", "source_file": "/Users/juandiego/Projects/Mentex app/screens/profile.jsx", "source_location": "L1207"}, {"caller_nid": "screens_profile_derivestatsfor", "callee": "from", "source_file": "/Users/juandiego/Projects/Mentex app/screens/profile.jsx", "source_location": "L1212"}, {"caller_nid": "screens_profile_derivestatsfor", "callee": "min", "source_file": "/Users/juandiego/Projects/Mentex app/screens/profile.jsx", "source_location": "L1221"}, {"caller_nid": "screens_profile_derivestatsfor", "callee": "floor", "source_file": "/Users/juandiego/Projects/Mentex app/screens/profile.jsx", "source_location": "L1221"}, {"caller_nid": "screens_profile_derivestatsfor", "callee": "from", "source_file": "/Users/juandiego/Projects/Mentex app/screens/profile.jsx", "source_location": "L1222"}, {"caller_nid": "screens_profile_derivestatsfor", "callee": "map", "source_file": "/Users/juandiego/Projects/Mentex app/screens/profile.jsx", "source_location": "L1228"}, {"caller_nid": "screens_profile_derivestatsfor", "callee": "max", "source_file": "/Users/juandiego/Projects/Mentex app/screens/profile.jsx", "source_location": "L1242"}, {"caller_nid": "screens_profile_derivestatsfor", "callee": "min", "source_file": "/Users/juandiego/Projects/Mentex app/screens/profile.jsx", "source_location": "L1242"}, {"caller_nid": "screens_profile_derivestatsfor", "callee": "round", "source_file": "/Users/juandiego/Projects/Mentex app/screens/profile.jsx", "source_location": "L1242"}, {"caller_nid": "screens_profile_derivestatsfor", "callee": "max", "source_file": "/Users/juandiego/Projects/Mentex app/screens/profile.jsx", "source_location": "L1243"}, {"caller_nid": "screens_profile_derivestatsfor", "callee": "round", "source_file": "/Users/juandiego/Projects/Mentex app/screens/profile.jsx", "source_location": "L1243"}, {"caller_nid": "screens_profile_derivestatsfor", "callee": "max", "source_file": "/Users/juandiego/Projects/Mentex app/screens/profile.jsx", "source_location": "L1244"}, {"caller_nid": "screens_profile_derivestatsfor", "callee": "round", "source_file": "/Users/juandiego/Projects/Mentex app/screens/profile.jsx", "source_location": "L1244"}, {"caller_nid": "screens_profile_derivestatsfor", "callee": "max", "source_file": "/Users/juandiego/Projects/Mentex app/screens/profile.jsx", "source_location": "L1245"}, {"caller_nid": "screens_profile_derivestatsfor", "callee": "round", "source_file": "/Users/juandiego/Projects/Mentex app/screens/profile.jsx", "source_location": "L1245"}, {"caller_nid": "screens_profile_derivestatsfor", "callee": "min", "source_file": "/Users/juandiego/Projects/Mentex app/screens/profile.jsx", "source_location": "L1245"}, {"caller_nid": "screens_profile_derivestatsfor", "callee": "String", "source_file": "/Users/juandiego/Projects/Mentex app/screens/profile.jsx", "source_location": "L1247"}, {"caller_nid": "screens_profile_derivestatsfor", "callee": "String", "source_file": "/Users/juandiego/Projects/Mentex app/screens/profile.jsx", "source_location": "L1248"}, {"caller_nid": "screens_profile_derivestatsfor", "callee": "String", "source_file": "/Users/juandiego/Projects/Mentex app/screens/profile.jsx", "source_location": "L1249"}, {"caller_nid": "screens_profile_derivestatsfor", "callee": "String", "source_file": "/Users/juandiego/Projects/Mentex app/screens/profile.jsx", "source_location": "L1250"}, {"caller_nid": "screens_profile_derivestatsfor", "callee": "map", "source_file": "/Users/juandiego/Projects/Mentex app/screens/profile.jsx", "source_location": "L1255"}, {"caller_nid": "screens_profile_derivestatsfor", "callee": "String", "source_file": "/Users/juandiego/Projects/Mentex app/screens/profile.jsx", "source_location": "L1260"}, {"caller_nid": "screens_profile_derivestatsfor", "callee": "String", "source_file": "/Users/juandiego/Projects/Mentex app/screens/profile.jsx", "source_location": "L1262"}, {"caller_nid": "screens_profile_profilestatstab", "callee": "split", "source_file": "/Users/juandiego/Projects/Mentex app/screens/profile.jsx", "source_location": "L1284"}, {"caller_nid": "screens_profile_profilestatstab", "callee": "useMemo", "source_file": "/Users/juandiego/Projects/Mentex app/screens/profile.jsx", "source_location": "L1334"}, {"caller_nid": "screens_profile_profilestatstab", "callee": "reduce", "source_file": "/Users/juandiego/Projects/Mentex app/screens/profile.jsx", "source_location": "L1345"}, {"caller_nid": "screens_profile_profilestatstab", "callee": "max", "source_file": "/Users/juandiego/Projects/Mentex app/screens/profile.jsx", "source_location": "L1346"}, {"caller_nid": "screens_profile_profilestatstab", "callee": "map", "source_file": "/Users/juandiego/Projects/Mentex app/screens/profile.jsx", "source_location": "L1346"}, {"caller_nid": "screens_profile_profilestatstab", "callee": "round", "source_file": "/Users/juandiego/Projects/Mentex app/screens/profile.jsx", "source_location": "L1347"}, {"caller_nid": "screens_profile_profilestatstab", "callee": "reduce", "source_file": "/Users/juandiego/Projects/Mentex app/screens/profile.jsx", "source_location": "L1353"}, {"caller_nid": "screens_profile_profilestatstab", "callee": "reduce", "source_file": "/Users/juandiego/Projects/Mentex app/screens/profile.jsx", "source_location": "L1360"}, {"caller_nid": "screens_profile_profilestatstab", "callee": "indexOf", "source_file": "/Users/juandiego/Projects/Mentex app/screens/profile.jsx", "source_location": "L1362"}, {"caller_nid": "screens_profile_profilestatstab", "callee": "max", "source_file": "/Users/juandiego/Projects/Mentex app/screens/profile.jsx", "source_location": "L1362"}, {"caller_nid": "screens_profile_profilestatstab", "callee": "filter", "source_file": "/Users/juandiego/Projects/Mentex app/screens/profile.jsx", "source_location": "L1370"}, {"caller_nid": "screens_profile_profilestatstab", "callee": "indexOf", "source_file": "/Users/juandiego/Projects/Mentex app/screens/profile.jsx", "source_location": "L1376"}, {"caller_nid": "screens_profile_profilestatstab", "callee": "max", "source_file": "/Users/juandiego/Projects/Mentex app/screens/profile.jsx", "source_location": "L1376"}, {"caller_nid": "screens_profile_profilestatstab", "callee": "max", "source_file": "/Users/juandiego/Projects/Mentex app/screens/profile.jsx", "source_location": "L1377"}, {"caller_nid": "screens_profile_profilestatstab", "callee": "reduce", "source_file": "/Users/juandiego/Projects/Mentex app/screens/profile.jsx", "source_location": "L1400"}, {"caller_nid": "screens_profile_profilestatstab", "callee": "indexOf", "source_file": "/Users/juandiego/Projects/Mentex app/screens/profile.jsx", "source_location": "L1401"}, {"caller_nid": "screens_profile_profilestatstab", "callee": "max", "source_file": "/Users/juandiego/Projects/Mentex app/screens/profile.jsx", "source_location": "L1401"}, {"caller_nid": "screens_profile_profilestatstab", "callee": "map", "source_file": "/Users/juandiego/Projects/Mentex app/screens/profile.jsx", "source_location": "L1417"}, {"caller_nid": "screens_profile_profilestatstab", "callee": "toFixed", "source_file": "/Users/juandiego/Projects/Mentex app/screens/profile.jsx", "source_location": "L1533"}, {"caller_nid": "screens_profile_profilestatstab", "callee": "map", "source_file": "/Users/juandiego/Projects/Mentex app/screens/profile.jsx", "source_location": "L1541"}, {"caller_nid": "screens_profile_profilestatstab", "callee": "toLocaleString", "source_file": "/Users/juandiego/Projects/Mentex app/screens/profile.jsx", "source_location": "L1589"}, {"caller_nid": "screens_profile_profilestatstab", "callee": "map", "source_file": "/Users/juandiego/Projects/Mentex app/screens/profile.jsx", "source_location": "L1614"}, {"caller_nid": "screens_profile_profilestatstab", "callee": "toFixed", "source_file": "/Users/juandiego/Projects/Mentex app/screens/profile.jsx", "source_location": "L1665"}, {"caller_nid": "screens_profile_profilestatstab", "callee": "toFixed", "source_file": "/Users/juandiego/Projects/Mentex app/screens/profile.jsx", "source_location": "L1667"}, {"caller_nid": "screens_profile_profilestatstab", "callee": "toFixed", "source_file": "/Users/juandiego/Projects/Mentex app/screens/profile.jsx", "source_location": "L1684"}, {"caller_nid": "screens_profile_profilestatstab", "callee": "map", "source_file": "/Users/juandiego/Projects/Mentex app/screens/profile.jsx", "source_location": "L1704"}, {"caller_nid": "screens_profile_profilestatstab", "callee": "map", "source_file": "/Users/juandiego/Projects/Mentex app/screens/profile.jsx", "source_location": "L1716"}, {"caller_nid": "screens_profile_profilestatstab", "callee": "map", "source_file": "/Users/juandiego/Projects/Mentex app/screens/profile.jsx", "source_location": "L1722"}, {"caller_nid": "screens_profile_profilestatstab", "callee": "round", "source_file": "/Users/juandiego/Projects/Mentex app/screens/profile.jsx", "source_location": "L1757"}, {"caller_nid": "screens_profile_profilestatstab", "callee": "map", "source_file": "/Users/juandiego/Projects/Mentex app/screens/profile.jsx", "source_location": "L1769"}, {"caller_nid": "screens_profile_profilestatstab", "callee": "map", "source_file": "/Users/juandiego/Projects/Mentex app/screens/profile.jsx", "source_location": "L1797"}, {"caller_nid": "screens_profile_profilestatstab", "callee": "fmtHour", "source_file": "/Users/juandiego/Projects/Mentex app/screens/profile.jsx", "source_location": "L1836"}, {"caller_nid": "screens_profile_profilestatstab", "callee": "map", "source_file": "/Users/juandiego/Projects/Mentex app/screens/profile.jsx", "source_location": "L1845"}, {"caller_nid": "screens_profile_profilestatstab", "callee": "map", "source_file": "/Users/juandiego/Projects/Mentex app/screens/profile.jsx", "source_location": "L1872"}, {"caller_nid": "screens_profile_profilestatstab", "callee": "map", "source_file": "/Users/juandiego/Projects/Mentex app/screens/profile.jsx", "source_location": "L1900"}, {"caller_nid": "screens_profile_profilestatstab", "callee": "map", "source_file": "/Users/juandiego/Projects/Mentex app/screens/profile.jsx", "source_location": "L2074"}, {"caller_nid": "screens_profile_profilestatstab", "callee": "toFixed", "source_file": "/Users/juandiego/Projects/Mentex app/screens/profile.jsx", "source_location": "L2130"}, {"caller_nid": "screens_profile_profilestatstab", "callee": "map", "source_file": "/Users/juandiego/Projects/Mentex app/screens/profile.jsx", "source_location": "L2167"}, {"caller_nid": "screens_profile_profilestatstab", "callee": "map", "source_file": "/Users/juandiego/Projects/Mentex app/screens/profile.jsx", "source_location": "L2179"}, {"caller_nid": "screens_profile_profilestatstab", "callee": "map", "source_file": "/Users/juandiego/Projects/Mentex app/screens/profile.jsx", "source_location": "L2185"}, {"caller_nid": "screens_profile_heronextachievement", "callee": "min", "source_file": "/Users/juandiego/Projects/Mentex app/screens/profile.jsx", "source_location": "L2214"}, {"caller_nid": "screens_profile_heronextachievement", "callee": "max", "source_file": "/Users/juandiego/Projects/Mentex app/screens/profile.jsx", "source_location": "L2215"}, {"caller_nid": "screens_profile_heronextachievement", "callee": "round", "source_file": "/Users/juandiego/Projects/Mentex app/screens/profile.jsx", "source_location": "L2290"}, {"caller_nid": "screens_profile_swipeableherocarousel", "callee": "useState", "source_file": "/Users/juandiego/Projects/Mentex app/screens/profile.jsx", "source_location": "L2303"}, {"caller_nid": "screens_profile_swipeableherocarousel", "callee": "useRef", "source_file": "/Users/juandiego/Projects/Mentex app/screens/profile.jsx", "source_location": "L2304"}, {"caller_nid": "screens_profile_swipeableherocarousel", "callee": "useEffect", "source_file": "/Users/juandiego/Projects/Mentex app/screens/profile.jsx", "source_location": "L2308"}, {"caller_nid": "screens_profile_swipeableherocarousel", "callee": "min", "source_file": "/Users/juandiego/Projects/Mentex app/screens/profile.jsx", "source_location": "L2314"}, {"caller_nid": "screens_profile_swipeableherocarousel", "callee": "map", "source_file": "/Users/juandiego/Projects/Mentex app/screens/profile.jsx", "source_location": "L2352"}, {"caller_nid": "screens_profile_awardstab", "callee": "useMemo", "source_file": "/Users/juandiego/Projects/Mentex app/screens/profile.jsx", "source_location": "L2389"}, {"caller_nid": "screens_profile_awardstab", "callee": "useMemo", "source_file": "/Users/juandiego/Projects/Mentex app/screens/profile.jsx", "source_location": "L2394"}, {"caller_nid": "screens_profile_awardstab", "callee": "useMemo", "source_file": "/Users/juandiego/Projects/Mentex app/screens/profile.jsx", "source_location": "L2401"}, {"caller_nid": "screens_profile_awardstab", "callee": "map", "source_file": "/Users/juandiego/Projects/Mentex app/screens/profile.jsx", "source_location": "L2420"}, {"caller_nid": "screens_profile_profilescreen", "callee": "useState", "source_file": "/Users/juandiego/Projects/Mentex app/screens/profile.jsx", "source_location": "L2466"}, {"caller_nid": "screens_profile_profilescreen", "callee": "useState", "source_file": "/Users/juandiego/Projects/Mentex app/screens/profile.jsx", "source_location": "L2467"}, {"caller_nid": "screens_profile_profilescreen", "callee": "useState", "source_file": "/Users/juandiego/Projects/Mentex app/screens/profile.jsx", "source_location": "L2468"}, {"caller_nid": "screens_profile_profilescreen", "callee": "useState", "source_file": "/Users/juandiego/Projects/Mentex app/screens/profile.jsx", "source_location": "L2469"}, {"caller_nid": "screens_profile_profilescreen", "callee": "useState", "source_file": "/Users/juandiego/Projects/Mentex app/screens/profile.jsx", "source_location": "L2470"}, {"caller_nid": "screens_profile_profilescreen", "callee": "useState", "source_file": "/Users/juandiego/Projects/Mentex app/screens/profile.jsx", "source_location": "L2471"}, {"caller_nid": "screens_profile_profilescreen", "callee": "useToast", "source_file": "/Users/juandiego/Projects/Mentex app/screens/profile.jsx", "source_location": "L2473"}, {"caller_nid": "screens_profile_profilescreen", "callee": "useReducer", "source_file": "/Users/juandiego/Projects/Mentex app/screens/profile.jsx", "source_location": "L2475"}, {"caller_nid": "screens_profile_profilescreen", "callee": "useEffect", "source_file": "/Users/juandiego/Projects/Mentex app/screens/profile.jsx", "source_location": "L2476"}, {"caller_nid": "screens_profile_profilescreen", "callee": "min", "source_file": "/Users/juandiego/Projects/Mentex app/screens/profile.jsx", "source_location": "L2485"}, {"caller_nid": "screens_profile_profilescreen", "callee": "countMyFollowers", "source_file": "/Users/juandiego/Projects/Mentex app/screens/profile.jsx", "source_location": "L2486"}, {"caller_nid": "screens_profile_profilescreen", "callee": "map", "source_file": "/Users/juandiego/Projects/Mentex app/screens/profile.jsx", "source_location": "L2747"}, {"caller_nid": "screens_profile_profilescreen", "callee": "toFixed", "source_file": "/Users/juandiego/Projects/Mentex app/screens/profile.jsx", "source_location": "L2750"}, {"caller_nid": "screens_profile_profilescreen", "callee": "toLocaleString", "source_file": "/Users/juandiego/Projects/Mentex app/screens/profile.jsx", "source_location": "L2750"}, {"caller_nid": "screens_profile_profilescreen", "callee": "filter", "source_file": "/Users/juandiego/Projects/Mentex app/screens/profile.jsx", "source_location": "L2817"}, {"caller_nid": "screens_profile_profilescreen", "callee": "map", "source_file": "/Users/juandiego/Projects/Mentex app/screens/profile.jsx", "source_location": "L2824"}, {"caller_nid": "screens_profile_profilescreen", "callee": "filter", "source_file": "/Users/juandiego/Projects/Mentex app/screens/profile.jsx", "source_location": "L2824"}, {"caller_nid": "screens_profile_profilescreen", "callee": "map", "source_file": "/Users/juandiego/Projects/Mentex app/screens/profile.jsx", "source_location": "L2860"}, {"caller_nid": "screens_profile_profilescreen", "callee": "map", "source_file": "/Users/juandiego/Projects/Mentex app/screens/profile.jsx", "source_location": "L2928"}, {"caller_nid": "screens_profile_profilescreen", "callee": "(() => {\n        const overlayRoot = typeof document !== 'undefined' ? document.getElementById('mtx-overlay-root') : null;\n        const sheet = (\n          <EditProfileSheet\n            profile={profile}\n            onClose={() => setEditOpen(false)}\n            onSave={handleSaveProfile}\n          />\n        );\n        return overlayRoot && window.ReactDOM\n          ? window.ReactDOM.createPortal(sheet, overlayRoot)\n          : sheet;\n      })", "source_file": "/Users/juandiego/Projects/Mentex app/screens/profile.jsx", "source_location": "L2948"}, {"caller_nid": "screens_profile_profilescreen", "callee": "(() => {\n        const ShareSheetCmp = window.ShareSheet;\n        const overlayRoot = typeof document !== 'undefined' ? document.getElementById('mtx-overlay-root') : null;\n        const sheet = <ShareSheetCmp item={shareEntity} onClose={() => setShareEntity(null)}/>;\n        return overlayRoot && window.ReactDOM\n          ? window.ReactDOM.createPortal(sheet, overlayRoot)\n          : sheet;\n      })", "source_file": "/Users/juandiego/Projects/Mentex app/screens/profile.jsx", "source_location": "L2963"}, {"caller_nid": "screens_profile_profilescreen", "callee": "(() => {\n        const overlayRoot = typeof document !== 'undefined' ? document.getElementById('mtx-overlay-root') : null;\n        const sheet = (\n          <window.AchievementSheet\n            achievement={achievementSheet}\n            onClose={() => setAchievementSheet(null)}\n          />\n        );\n        return overlayRoot && window.ReactDOM\n          ? window.ReactDOM.createPortal(sheet, overlayRoot)\n          : sheet;\n      })", "source_file": "/Users/juandiego/Projects/Mentex app/screens/profile.jsx", "source_location": "L2973"}, {"caller_nid": "screens_profile_profilescreen", "callee": "(() => {\n        const overlayRoot = typeof document !== 'undefined' ? document.getElementById('mtx-overlay-root') : null;\n        // Profile enriquecido con hours para que los sheets puedan derivar datos\n        const enrichedProfile = {\n          ...profile,\n          hours: hoursLearned,\n          followers: followersCount,\n        };\n        let sheet = null;\n        if (statSheet === 'level' && window.LevelSheet) {\n          sheet = <window.LevelSheet profile={enrichedProfile} onClose={() => setStatSheet(null)}/>;\n        } else if (statSheet === 'hours' && window.HoursSheet) {\n          sheet = <window.HoursSheet profile={enrichedProfile} onClose={() => setStatSheet(null)}/>;\n        } else if (statSheet === 'followers' && window.FollowersSheet) {\n          sheet = <window.FollowersSheet profile={enrichedProfile} onClose={() => setStatSheet(null)} isOwn={true}/>;\n        }\n        if (!sheet) return null;\n        return overlayRoot && window.ReactDOM\n          ? window.ReactDOM.createPortal(sheet, overlayRoot)\n          : sheet;\n      })", "source_file": "/Users/juandiego/Projects/Mentex app/screens/profile.jsx", "source_location": "L2987"}, {"caller_nid": "screens_profile_profilescreen", "callee": "(() => {\n        const ThreadCmp = window.ReviewThreadScreen;\n        const overlayRoot = typeof document !== 'undefined' ? document.getElementById('mtx-overlay-root') : null;\n        const screen = (\n          <ThreadCmp\n            review={threadReview}\n            onClose={() => setThreadReview(null)}\n            onItemTap={(item) => {\n              setThreadReview(null);\n              setTimeout(() => handleItemTap({ itemId: item.id }), 200);\n            }}\n            onShareTap={(entity) => setShareEntity(entity)}\n            onAuthorTap={() => { /* es el propio user \u2014 no navega */ }}\n          />\n        );\n        return overlayRoot && window.ReactDOM\n          ? window.ReactDOM.createPortal(screen, overlayRoot)\n          : screen;\n      })", "source_file": "/Users/juandiego/Projects/Mentex app/screens/profile.jsx", "source_location": "L3010"}]}