{"nodes": [{"id": "users_juandiego_projects_mentex_app_screens_ia_tasks_jsx", "label": "ia-tasks.jsx", "file_type": "code", "source_file": "/Users/juandiego/Projects/Mentex app/screens/ia-tasks.jsx", "source_location": "L1"}, {"id": "screens_ia_tasks_formatrelative", "label": "_formatRelative()", "file_type": "code", "source_file": "/Users/juandiego/Projects/Mentex app/screens/ia-tasks.jsx", "source_location": "L35"}, {"id": "screens_ia_tasks_formattime", "label": "_formatTime()", "file_type": "code", "source_file": "/Users/juandiego/Projects/Mentex app/screens/ia-tasks.jsx", "source_location": "L60"}, {"id": "screens_ia_tasks_formatduration", "label": "_formatDuration()", "file_type": "code", "source_file": "/Users/juandiego/Projects/Mentex app/screens/ia-tasks.jsx", "source_location": "L68"}, {"id": "screens_ia_tasks_genid", "label": "_genId()", "file_type": "code", "source_file": "/Users/juandiego/Projects/Mentex app/screens/ia-tasks.jsx", "source_location": "L77"}, {"id": "screens_ia_tasks_emit", "label": "_emit()", "file_type": "code", "source_file": "/Users/juandiego/Projects/Mentex app/screens/ia-tasks.jsx", "source_location": "L227"}, {"id": "screens_ia_tasks_useiatasks", "label": "useIATasks()", "file_type": "code", "source_file": "/Users/juandiego/Projects/Mentex app/screens/ia-tasks.jsx", "source_location": "L371"}, {"id": "screens_ia_tasks_activetaskcard", "label": "ActiveTaskCard()", "file_type": "code", "source_file": "/Users/juandiego/Projects/Mentex app/screens/ia-tasks.jsx", "source_location": "L388"}, {"id": "screens_ia_tasks_scheduledtaskcard", "label": "ScheduledTaskCard()", "file_type": "code", "source_file": "/Users/juandiego/Projects/Mentex app/screens/ia-tasks.jsx", "source_location": "L505"}, {"id": "screens_ia_tasks_pendingtaskcard", "label": "PendingTaskCard()", "file_type": "code", "source_file": "/Users/juandiego/Projects/Mentex app/screens/ia-tasks.jsx", "source_location": "L576"}, {"id": "screens_ia_tasks_historytaskitem", "label": "HistoryTaskItem()", "file_type": "code", "source_file": "/Users/juandiego/Projects/Mentex app/screens/ia-tasks.jsx", "source_location": "L725"}, {"id": "screens_ia_tasks_taskssheet", "label": "TasksSheet()", "file_type": "code", "source_file": "/Users/juandiego/Projects/Mentex app/screens/ia-tasks.jsx", "source_location": "L830"}, {"id": "screens_ia_tasks_tasksemptystate", "label": "TasksEmptyState()", "file_type": "code", "source_file": "/Users/juandiego/Projects/Mentex app/screens/ia-tasks.jsx", "source_location": "L1112"}, {"id": "screens_ia_tasks_iatasksicon", "label": "IATasksIcon()", "file_type": "code", "source_file": "/Users/juandiego/Projects/Mentex app/screens/ia-tasks.jsx", "source_location": "L1146"}], "edges": [{"source": "users_juandiego_projects_mentex_app_screens_ia_tasks_jsx", "target": "screens_ia_tasks_formatrelative", "relation": "contains", "confidence": "EXTRACTED", "source_file": "/Users/juandiego/Projects/Mentex app/screens/ia-tasks.jsx", "source_location": "L35", "weight": 1.0}, {"source": "users_juandiego_projects_mentex_app_screens_ia_tasks_jsx", "target": "screens_ia_tasks_formattime", "relation": "contains", "confidence": "EXTRACTED", "source_file": "/Users/juandiego/Projects/Mentex app/screens/ia-tasks.jsx", "source_location": "L60", "weight": 1.0}, {"source": "users_juandiego_projects_mentex_app_screens_ia_tasks_jsx", "target": "screens_ia_tasks_formatduration", "relation": "contains", "confidence": "EXTRACTED", "source_file": "/Users/juandiego/Projects/Mentex app/screens/ia-tasks.jsx", "source_location": "L68", "weight": 1.0}, {"source": "users_juandiego_projects_mentex_app_screens_ia_tasks_jsx", "target": "screens_ia_tasks_genid", "relation": "contains", "confidence": "EXTRACTED", "source_file": "/Users/juandiego/Projects/Mentex app/screens/ia-tasks.jsx", "source_location": "L77", "weight": 1.0}, {"source": "users_juandiego_projects_mentex_app_screens_ia_tasks_jsx", "target": "screens_ia_tasks_emit", "relation": "contains", "confidence": "EXTRACTED", "source_file": "/Users/juandiego/Projects/Mentex app/screens/ia-tasks.jsx", "source_location": "L227", "weight": 1.0}, {"source": "users_juandiego_projects_mentex_app_screens_ia_tasks_jsx", "target": "screens_ia_tasks_useiatasks", "relation": "contains", "confidence": "EXTRACTED", "source_file": "/Users/juandiego/Projects/Mentex app/screens/ia-tasks.jsx", "source_location": "L371", "weight": 1.0}, {"source": "users_juandiego_projects_mentex_app_screens_ia_tasks_jsx", "target": "screens_ia_tasks_activetaskcard", "relation": "contains", "confidence": "EXTRACTED", "source_file": "/Users/juandiego/Projects/Mentex app/screens/ia-tasks.jsx", "source_location": "L388", "weight": 1.0}, {"source": "users_juandiego_projects_mentex_app_screens_ia_tasks_jsx", "target": "screens_ia_tasks_scheduledtaskcard", "relation": "contains", "confidence": "EXTRACTED", "source_file": "/Users/juandiego/Projects/Mentex app/screens/ia-tasks.jsx", "source_location": "L505", "weight": 1.0}, {"source": "users_juandiego_projects_mentex_app_screens_ia_tasks_jsx", "target": "screens_ia_tasks_pendingtaskcard", "relation": "contains", "confidence": "EXTRACTED", "source_file": "/Users/juandiego/Projects/Mentex app/screens/ia-tasks.jsx", "source_location": "L576", "weight": 1.0}, {"source": "users_juandiego_projects_mentex_app_screens_ia_tasks_jsx", "target": "screens_ia_tasks_historytaskitem", "relation": "contains", "confidence": "EXTRACTED", "source_file": "/Users/juandiego/Projects/Mentex app/screens/ia-tasks.jsx", "source_location": "L725", "weight": 1.0}, {"source": "users_juandiego_projects_mentex_app_screens_ia_tasks_jsx", "target": "screens_ia_tasks_taskssheet", "relation": "contains", "confidence": "EXTRACTED", "source_file": "/Users/juandiego/Projects/Mentex app/screens/ia-tasks.jsx", "source_location": "L830", "weight": 1.0}, {"source": "users_juandiego_projects_mentex_app_screens_ia_tasks_jsx", "target": "screens_ia_tasks_tasksemptystate", "relation": "contains", "confidence": "EXTRACTED", "source_file": "/Users/juandiego/Projects/Mentex app/screens/ia-tasks.jsx", "source_location": "L1112", "weight": 1.0}, {"source": "users_juandiego_projects_mentex_app_screens_ia_tasks_jsx", "target": "screens_ia_tasks_iatasksicon", "relation": "contains", "confidence": "EXTRACTED", "source_file": "/Users/juandiego/Projects/Mentex app/screens/ia-tasks.jsx", "source_location": "L1146", "weight": 1.0}, {"source": "screens_ia_tasks_taskssheet", "target": "screens_ia_tasks_useiatasks", "relation": "calls", "confidence": "EXTRACTED", "source_file": "/Users/juandiego/Projects/Mentex app/screens/ia-tasks.jsx", "source_location": "L833", "weight": 1.0}, {"source": "screens_ia_tasks_iatasksicon", "target": "screens_ia_tasks_useiatasks", "relation": "calls", "confidence": "EXTRACTED", "source_file": "/Users/juandiego/Projects/Mentex app/screens/ia-tasks.jsx", "source_location": "L1148", "weight": 1.0}], "raw_calls": [{"caller_nid": "screens_ia_tasks_formatrelative", "callee": "now", "source_file": "/Users/juandiego/Projects/Mentex app/screens/ia-tasks.jsx", "source_location": "L37"}, {"caller_nid": "screens_ia_tasks_formatrelative", "callee": "abs", "source_file": "/Users/juandiego/Projects/Mentex app/screens/ia-tasks.jsx", "source_location": "L38"}, {"caller_nid": "screens_ia_tasks_formatrelative", "callee": "floor", "source_file": "/Users/juandiego/Projects/Mentex app/screens/ia-tasks.jsx", "source_location": "L43"}, {"caller_nid": "screens_ia_tasks_formatrelative", "callee": "floor", "source_file": "/Users/juandiego/Projects/Mentex app/screens/ia-tasks.jsx", "source_location": "L47"}, {"caller_nid": "screens_ia_tasks_formatrelative", "callee": "floor", "source_file": "/Users/juandiego/Projects/Mentex app/screens/ia-tasks.jsx", "source_location": "L48"}, {"caller_nid": "screens_ia_tasks_formatrelative", "callee": "floor", "source_file": "/Users/juandiego/Projects/Mentex app/screens/ia-tasks.jsx", "source_location": "L54"}, {"caller_nid": "screens_ia_tasks_formatrelative", "callee": "floor", "source_file": "/Users/juandiego/Projects/Mentex app/screens/ia-tasks.jsx", "source_location": "L57"}, {"caller_nid": "screens_ia_tasks_formattime", "callee": "getHours", "source_file": "/Users/juandiego/Projects/Mentex app/screens/ia-tasks.jsx", "source_location": "L63"}, {"caller_nid": "screens_ia_tasks_formattime", "callee": "getMinutes", "source_file": "/Users/juandiego/Projects/Mentex app/screens/ia-tasks.jsx", "source_location": "L64"}, {"caller_nid": "screens_ia_tasks_formatduration", "callee": "toFixed", "source_file": "/Users/juandiego/Projects/Mentex app/screens/ia-tasks.jsx", "source_location": "L71"}, {"caller_nid": "screens_ia_tasks_formatduration", "callee": "floor", "source_file": "/Users/juandiego/Projects/Mentex app/screens/ia-tasks.jsx", "source_location": "L72"}, {"caller_nid": "screens_ia_tasks_formatduration", "callee": "floor", "source_file": "/Users/juandiego/Projects/Mentex app/screens/ia-tasks.jsx", "source_location": "L73"}, {"caller_nid": "screens_ia_tasks_genid", "callee": "toString", "source_file": "/Users/juandiego/Projects/Mentex app/screens/ia-tasks.jsx", "source_location": "L78"}, {"caller_nid": "screens_ia_tasks_genid", "callee": "now", "source_file": "/Users/juandiego/Projects/Mentex app/screens/ia-tasks.jsx", "source_location": "L78"}, {"caller_nid": "screens_ia_tasks_genid", "callee": "slice", "source_file": "/Users/juandiego/Projects/Mentex app/screens/ia-tasks.jsx", "source_location": "L78"}, {"caller_nid": "screens_ia_tasks_genid", "callee": "toString", "source_file": "/Users/juandiego/Projects/Mentex app/screens/ia-tasks.jsx", "source_location": "L78"}, {"caller_nid": "screens_ia_tasks_genid", "callee": "random", "source_file": "/Users/juandiego/Projects/Mentex app/screens/ia-tasks.jsx", "source_location": "L78"}, {"caller_nid": "screens_ia_tasks_emit", "callee": "dispatchEvent", "source_file": "/Users/juandiego/Projects/Mentex app/screens/ia-tasks.jsx", "source_location": "L228"}, {"caller_nid": "screens_ia_tasks_useiatasks", "callee": "useReducer", "source_file": "/Users/juandiego/Projects/Mentex app/screens/ia-tasks.jsx", "source_location": "L372"}, {"caller_nid": "screens_ia_tasks_useiatasks", "callee": "useEffect", "source_file": "/Users/juandiego/Projects/Mentex app/screens/ia-tasks.jsx", "source_location": "L373"}, {"caller_nid": "screens_ia_tasks_useiatasks", "callee": "force", "source_file": "/Users/juandiego/Projects/Mentex app/screens/ia-tasks.jsx", "source_location": "L374"}, {"caller_nid": "screens_ia_tasks_useiatasks", "callee": "addEventListener", "source_file": "/Users/juandiego/Projects/Mentex app/screens/ia-tasks.jsx", "source_location": "L375"}, {"caller_nid": "screens_ia_tasks_useiatasks", "callee": "removeEventListener", "source_file": "/Users/juandiego/Projects/Mentex app/screens/ia-tasks.jsx", "source_location": "L376"}, {"caller_nid": "screens_ia_tasks_useiatasks", "callee": "snapshot", "source_file": "/Users/juandiego/Projects/Mentex app/screens/ia-tasks.jsx", "source_location": "L379"}, {"caller_nid": "screens_ia_tasks_activetaskcard", "callee": "getAccent", "source_file": "/Users/juandiego/Projects/Mentex app/screens/ia-tasks.jsx", "source_location": "L390"}, {"caller_nid": "screens_ia_tasks_activetaskcard", "callee": "formatDuration", "source_file": "/Users/juandiego/Projects/Mentex app/screens/ia-tasks.jsx", "source_location": "L391"}, {"caller_nid": "screens_ia_tasks_activetaskcard", "callee": "now", "source_file": "/Users/juandiego/Projects/Mentex app/screens/ia-tasks.jsx", "source_location": "L391"}, {"caller_nid": "screens_ia_tasks_activetaskcard", "callee": "now", "source_file": "/Users/juandiego/Projects/Mentex app/screens/ia-tasks.jsx", "source_location": "L391"}, {"caller_nid": "screens_ia_tasks_activetaskcard", "callee": "round", "source_file": "/Users/juandiego/Projects/Mentex app/screens/ia-tasks.jsx", "source_location": "L466"}, {"caller_nid": "screens_ia_tasks_activetaskcard", "callee": "formatRelative", "source_file": "/Users/juandiego/Projects/Mentex app/screens/ia-tasks.jsx", "source_location": "L494"}, {"caller_nid": "screens_ia_tasks_scheduledtaskcard", "callee": "getAccent", "source_file": "/Users/juandiego/Projects/Mentex app/screens/ia-tasks.jsx", "source_location": "L507"}, {"caller_nid": "screens_ia_tasks_scheduledtaskcard", "callee": "formatRelative", "source_file": "/Users/juandiego/Projects/Mentex app/screens/ia-tasks.jsx", "source_location": "L508"}, {"caller_nid": "screens_ia_tasks_scheduledtaskcard", "callee": "formatTime", "source_file": "/Users/juandiego/Projects/Mentex app/screens/ia-tasks.jsx", "source_location": "L509"}, {"caller_nid": "screens_ia_tasks_pendingtaskcard", "callee": "getAccent", "source_file": "/Users/juandiego/Projects/Mentex app/screens/ia-tasks.jsx", "source_location": "L580"}, {"caller_nid": "screens_ia_tasks_pendingtaskcard", "callee": "formatRelative", "source_file": "/Users/juandiego/Projects/Mentex app/screens/ia-tasks.jsx", "source_location": "L682"}, {"caller_nid": "screens_ia_tasks_pendingtaskcard", "callee": "preventDefault", "source_file": "/Users/juandiego/Projects/Mentex app/screens/ia-tasks.jsx", "source_location": "L687"}, {"caller_nid": "screens_ia_tasks_pendingtaskcard", "callee": "onDismiss", "source_file": "/Users/juandiego/Projects/Mentex app/screens/ia-tasks.jsx", "source_location": "L687"}, {"caller_nid": "screens_ia_tasks_pendingtaskcard", "callee": "preventDefault", "source_file": "/Users/juandiego/Projects/Mentex app/screens/ia-tasks.jsx", "source_location": "L702"}, {"caller_nid": "screens_ia_tasks_pendingtaskcard", "callee": "onApprove", "source_file": "/Users/juandiego/Projects/Mentex app/screens/ia-tasks.jsx", "source_location": "L702"}, {"caller_nid": "screens_ia_tasks_historytaskitem", "callee": "getAccent", "source_file": "/Users/juandiego/Projects/Mentex app/screens/ia-tasks.jsx", "source_location": "L728"}, {"caller_nid": "screens_ia_tasks_historytaskitem", "callee": "formatRelative", "source_file": "/Users/juandiego/Projects/Mentex app/screens/ia-tasks.jsx", "source_location": "L815"}, {"caller_nid": "screens_ia_tasks_historytaskitem", "callee": "formatDuration", "source_file": "/Users/juandiego/Projects/Mentex app/screens/ia-tasks.jsx", "source_location": "L817"}, {"caller_nid": "screens_ia_tasks_taskssheet", "callee": "getStats", "source_file": "/Users/juandiego/Projects/Mentex app/screens/ia-tasks.jsx", "source_location": "L837"}, {"caller_nid": "screens_ia_tasks_taskssheet", "callee": "getActive", "source_file": "/Users/juandiego/Projects/Mentex app/screens/ia-tasks.jsx", "source_location": "L838"}, {"caller_nid": "screens_ia_tasks_taskssheet", "callee": "getScheduled", "source_file": "/Users/juandiego/Projects/Mentex app/screens/ia-tasks.jsx", "source_location": "L839"}, {"caller_nid": "screens_ia_tasks_taskssheet", "callee": "getPending", "source_file": "/Users/juandiego/Projects/Mentex app/screens/ia-tasks.jsx", "source_location": "L840"}, {"caller_nid": "screens_ia_tasks_taskssheet", "callee": "getHistory", "source_file": "/Users/juandiego/Projects/Mentex app/screens/ia-tasks.jsx", "source_location": "L841"}, {"caller_nid": "screens_ia_tasks_taskssheet", "callee": "useState", "source_file": "/Users/juandiego/Projects/Mentex app/screens/ia-tasks.jsx", "source_location": "L843"}, {"caller_nid": "screens_ia_tasks_taskssheet", "callee": "_useToast", "source_file": "/Users/juandiego/Projects/Mentex app/screens/ia-tasks.jsx", "source_location": "L848"}, {"caller_nid": "screens_ia_tasks_taskssheet", "callee": "useRef", "source_file": "/Users/juandiego/Projects/Mentex app/screens/ia-tasks.jsx", "source_location": "L851"}, {"caller_nid": "screens_ia_tasks_taskssheet", "callee": "useEffect", "source_file": "/Users/juandiego/Projects/Mentex app/screens/ia-tasks.jsx", "source_location": "L852"}, {"caller_nid": "screens_ia_tasks_taskssheet", "callee": "useEffect", "source_file": "/Users/juandiego/Projects/Mentex app/screens/ia-tasks.jsx", "source_location": "L853"}, {"caller_nid": "screens_ia_tasks_taskssheet", "callee": "current", "source_file": "/Users/juandiego/Projects/Mentex app/screens/ia-tasks.jsx", "source_location": "L859"}, {"caller_nid": "screens_ia_tasks_taskssheet", "callee": "addEventListener", "source_file": "/Users/juandiego/Projects/Mentex app/screens/ia-tasks.jsx", "source_location": "L861"}, {"caller_nid": "screens_ia_tasks_taskssheet", "callee": "removeEventListener", "source_file": "/Users/juandiego/Projects/Mentex app/screens/ia-tasks.jsx", "source_location": "L862"}, {"caller_nid": "screens_ia_tasks_taskssheet", "callee": "useEffect", "source_file": "/Users/juandiego/Projects/Mentex app/screens/ia-tasks.jsx", "source_location": "L866"}, {"caller_nid": "screens_ia_tasks_taskssheet", "callee": "join", "source_file": "/Users/juandiego/Projects/Mentex app/screens/ia-tasks.jsx", "source_location": "L876"}, {"caller_nid": "screens_ia_tasks_taskssheet", "callee": "map", "source_file": "/Users/juandiego/Projects/Mentex app/screens/ia-tasks.jsx", "source_location": "L876"}, {"caller_nid": "screens_ia_tasks_taskssheet", "callee": "useEffect", "source_file": "/Users/juandiego/Projects/Mentex app/screens/ia-tasks.jsx", "source_location": "L877"}, {"caller_nid": "screens_ia_tasks_taskssheet", "callee": "setInterval", "source_file": "/Users/juandiego/Projects/Mentex app/screens/ia-tasks.jsx", "source_location": "L879"}, {"caller_nid": "screens_ia_tasks_taskssheet", "callee": "tickActive", "source_file": "/Users/juandiego/Projects/Mentex app/screens/ia-tasks.jsx", "source_location": "L880"}, {"caller_nid": "screens_ia_tasks_taskssheet", "callee": "clearInterval", "source_file": "/Users/juandiego/Projects/Mentex app/screens/ia-tasks.jsx", "source_location": "L882"}, {"caller_nid": "screens_ia_tasks_taskssheet", "callee": "useRef", "source_file": "/Users/juandiego/Projects/Mentex app/screens/ia-tasks.jsx", "source_location": "L886"}, {"caller_nid": "screens_ia_tasks_taskssheet", "callee": "approvePending", "source_file": "/Users/juandiego/Projects/Mentex app/screens/ia-tasks.jsx", "source_location": "L888"}, {"caller_nid": "screens_ia_tasks_taskssheet", "callee": "show", "source_file": "/Users/juandiego/Projects/Mentex app/screens/ia-tasks.jsx", "source_location": "L889"}, {"caller_nid": "screens_ia_tasks_taskssheet", "callee": "setSub", "source_file": "/Users/juandiego/Projects/Mentex app/screens/ia-tasks.jsx", "source_location": "L890"}, {"caller_nid": "screens_ia_tasks_taskssheet", "callee": "dismissPending", "source_file": "/Users/juandiego/Projects/Mentex app/screens/ia-tasks.jsx", "source_location": "L893"}, {"caller_nid": "screens_ia_tasks_taskssheet", "callee": "show", "source_file": "/Users/juandiego/Projects/Mentex app/screens/ia-tasks.jsx", "source_location": "L894"}, {"caller_nid": "screens_ia_tasks_taskssheet", "callee": "retryHistory", "source_file": "/Users/juandiego/Projects/Mentex app/screens/ia-tasks.jsx", "source_location": "L899"}, {"caller_nid": "screens_ia_tasks_taskssheet", "callee": "show", "source_file": "/Users/juandiego/Projects/Mentex app/screens/ia-tasks.jsx", "source_location": "L900"}, {"caller_nid": "screens_ia_tasks_taskssheet", "callee": "setSub", "source_file": "/Users/juandiego/Projects/Mentex app/screens/ia-tasks.jsx", "source_location": "L901"}, {"caller_nid": "screens_ia_tasks_taskssheet", "callee": "setTimeout", "source_file": "/Users/juandiego/Projects/Mentex app/screens/ia-tasks.jsx", "source_location": "L902"}, {"caller_nid": "screens_ia_tasks_taskssheet", "callee": "map", "source_file": "/Users/juandiego/Projects/Mentex app/screens/ia-tasks.jsx", "source_location": "L918"}, {"caller_nid": "screens_ia_tasks_taskssheet", "callee": "map", "source_file": "/Users/juandiego/Projects/Mentex app/screens/ia-tasks.jsx", "source_location": "L926"}, {"caller_nid": "screens_ia_tasks_taskssheet", "callee": "handleApprove", "source_file": "/Users/juandiego/Projects/Mentex app/screens/ia-tasks.jsx", "source_location": "L931"}, {"caller_nid": "screens_ia_tasks_taskssheet", "callee": "handleDismiss", "source_file": "/Users/juandiego/Projects/Mentex app/screens/ia-tasks.jsx", "source_location": "L932"}, {"caller_nid": "screens_ia_tasks_taskssheet", "callee": "map", "source_file": "/Users/juandiego/Projects/Mentex app/screens/ia-tasks.jsx", "source_location": "L943"}, {"caller_nid": "screens_ia_tasks_taskssheet", "callee": "map", "source_file": "/Users/juandiego/Projects/Mentex app/screens/ia-tasks.jsx", "source_location": "L951"}, {"caller_nid": "screens_ia_tasks_taskssheet", "callee": "handleRetry", "source_file": "/Users/juandiego/Projects/Mentex app/screens/ia-tasks.jsx", "source_location": "L956"}, {"caller_nid": "screens_ia_tasks_taskssheet", "callee": "getElementById", "source_file": "/Users/juandiego/Projects/Mentex app/screens/ia-tasks.jsx", "source_location": "L966"}, {"caller_nid": "screens_ia_tasks_taskssheet", "callee": "preventDefault", "source_file": "/Users/juandiego/Projects/Mentex app/screens/ia-tasks.jsx", "source_location": "L992"}, {"caller_nid": "screens_ia_tasks_taskssheet", "callee": "onClose", "source_file": "/Users/juandiego/Projects/Mentex app/screens/ia-tasks.jsx", "source_location": "L992"}, {"caller_nid": "screens_ia_tasks_taskssheet", "callee": "map", "source_file": "/Users/juandiego/Projects/Mentex app/screens/ia-tasks.jsx", "source_location": "L1053"}, {"caller_nid": "screens_ia_tasks_taskssheet", "callee": "setSub", "source_file": "/Users/juandiego/Projects/Mentex app/screens/ia-tasks.jsx", "source_location": "L1061"}, {"caller_nid": "screens_ia_tasks_taskssheet", "callee": "createPortal", "source_file": "/Users/juandiego/Projects/Mentex app/screens/ia-tasks.jsx", "source_location": "L1104"}, {"caller_nid": "screens_ia_tasks_iatasksicon", "callee": "getStats", "source_file": "/Users/juandiego/Projects/Mentex app/screens/ia-tasks.jsx", "source_location": "L1149"}]}